ImputerAPI/__init__.py
ImputerAPI/imputerApi.py
ImputerApi-0.0.3.dist-info/LICENSE
ImputerApi-0.0.3.dist-info/METADATA
ImputerApi-0.0.3.dist-info/WHEEL
ImputerApi-0.0.3.dist-info/top_level.txt
ImputerApi-0.0.3.dist-info/RECORD
