Metadata-Version: 2.1
Name: ImputerApi
Version: 0.0.3
Summary: Data Imputer API
Home-page: https://github.com/mannasoumya/imputerApi
Author: Soumya Manna
Author-email: soumyamanna@hotmail.com
License: UNKNOWN
Platform: UNKNOWN
Classifier: Programming Language :: Python :: 3
Classifier: License :: OSI Approved :: MIT License
Classifier: Operating System :: OS Independent
Requires-Python: >=3.5
